nbhelper_onebot-0.1.0.dist-info/METADATA
nbhelper_onebot-0.1.0.dist-info/WHEEL
nbhelper_onebot-0.1.0.dist-info/entry_points.txt
nbhelper_onebot-0.1.0.dist-info/licenses/LICENSE
nbhelper_onebot/__init__.py
nbhelper_onebot/configs/__init__.py
nbhelper_onebot/errors/__init__.py
nbhelper_onebot/models/__init__.py
nbhelper_onebot/models/friend.py
nbhelper_onebot/models/group.py
nbhelper_onebot/models/group_member.py
nbhelper_onebot/obapi/__init__.py
nbhelper_onebot/social.py
nbhelper_onebot/utils.py
nbhelper_onebot-0.1.0.dist-info/RECORD
